openreview_dl/__init__.py
openreview_dl/cli.py
openreview_dl-0.2.0.dist-info/METADATA
openreview_dl-0.2.0.dist-info/WHEEL
openreview_dl-0.2.0.dist-info/entry_points.txt
openreview_dl-0.2.0.dist-info/licenses/LICENSE
openreview_dl-0.2.0.dist-info/RECORD
