Metadata-Version: 2.4
Name: openreview-dl
Version: 0.2.0
Summary: Download OpenReview paper reviews and rebuttals as formatted documents
Project-URL: Homepage, https://github.com/dwahdany/openreview-dl
Project-URL: Repository, https://github.com/dwahdany/openreview-dl
Project-URL: Issues, https://github.com/dwahdany/openreview-dl/issues
Author: Dariush Wahdany
License: BSD-3-Clause
License-File: LICENSE
Keywords: academic,downloader,openreview,papers,reviews
Classifier: Development Status :: 4 - Beta
Classifier: Intended Audience :: Science/Research
Classifier: License :: OSI Approved :: BSD License
Classifier: Programming Language :: Python :: 3
Classifier: Programming Language :: Python :: 3.11
Classifier: Programming Language :: Python :: 3.12
Classifier: Programming Language :: Python :: 3.13
Classifier: Topic :: Scientific/Engineering
Requires-Python: >=3.11
Requires-Dist: cryptography>=44.0.2
Requires-Dist: markdown>=3.7
Requires-Dist: openreview-py>=1.47.1
Requires-Dist: pypandoc>=1.15
Requires-Dist: urllib3>=2.0.0
